wordweaver/__init__.py
wordweaver/app.py
wordweaver/cli.py
wordweaver/config.py
wordweaver/data.py
wordweaver/exceptions.py
wordweaver/log.py
wordweaver/views.py
wordweaver/buildtools/__init__.py
wordweaver/buildtools/chart_data_req.py
wordweaver/buildtools/file_maker.py
wordweaver/buildtools/flask_template_gen.py
wordweaver/buildtools/swagger_spec_gen.py
wordweaver/fst/__init__.py
wordweaver/fst/decoder.py
wordweaver/fst/encoder.py
wordweaver/fst/english_generator.py
wordweaver/fst/foma.py
wordweaver/fst/six_1_11_0.py
wordweaver/fst/utils/__init__.py
wordweaver/fst/utils/abstract_fst_access.py
wordweaver/fst/utils/compare_strings.py
wordweaver/fst/utils/foma_access.py
wordweaver/fst/utils/foma_access_python.py
wordweaver/resources/__init__.py
wordweaver/resources/affix.py
wordweaver/resources/conjugate.py
wordweaver/resources/pronoun.py
wordweaver/resources/utils.py
wordweaver/resources/verb.py
wordweaver/sample/configs/build_config.yaml
wordweaver/sample/configs/env_config.yaml
wordweaver/sample/configs/interface_config.yaml
wordweaver/sample/configs/lang_config.yaml
wordweaver/sample/data/api_data/affixes.json
wordweaver/sample/data/api_data/pronouns.json
wordweaver/sample/data/api_data/verbs.json
wordweaver/sample/data/fomabins/toy-kawe-stressed-markup.fomabin
wordweaver/sample/data/swagger/.DS_Store
wordweaver/sample/data/swagger/swagger-pre.json
wordweaver/sample/data/swagger/__pycache__/__init__.cpython-37.pyc
wordweaver/sample/data/swagger/generated/swagger.json
wordweaver/static/.DS_Store
wordweaver/static/__init__.py
wordweaver/static/swagger.json
wordweaver/static/__pycache__/__init__.cpython-37.pyc
wordweaver/static/swagger-ui/favicon-16x16.png
wordweaver/static/swagger-ui/favicon-32x32.png
wordweaver/static/swagger-ui/swagger-ui-bundle.js
wordweaver/static/swagger-ui/swagger-ui-standalone-preset.js
wordweaver/static/swagger-ui/swagger-ui.css
wordweaver/static/web/.DS_Store
wordweaver/static/web/assets/bg.jpg
wordweaver/templates/404.html
wordweaver-0.0.35.dist-info/LICENSE
wordweaver-0.0.35.dist-info/METADATA
wordweaver-0.0.35.dist-info/WHEEL
wordweaver-0.0.35.dist-info/entry_points.txt
wordweaver-0.0.35.dist-info/top_level.txt
wordweaver-0.0.35.dist-info/RECORD
