Metadata-Version: 2.1
Name: wordweaver
Version: 0.0.35
Summary: WordWeaver: A tool for creating RESTful morphology web services
Home-page: https://github.com/nrc-cnrc/wordweaver
Author: Aidan Pine, Anna Kazantseva
Author-email: aidan.pine@nrc-cnrc.gc.ca, anna.kazantseva@nrc-cnrc.gc.ca
License: MIT
Platform: UNKNOWN
Requires-Python: >=3.6
Requires-Dist: Flask (>=1.0.2)
Requires-Dist: flask-restful
Requires-Dist: flask-cors
Requires-Dist: jsonpointer
Requires-Dist: python-slugify
Requires-Dist: six
Requires-Dist: gunicorn
Requires-Dist: requests
Requires-Dist: coloredlogs
Requires-Dist: flask-talisman
Requires-Dist: python-docx
Requires-Dist: pylatexenc
Requires-Dist: jinja2
Requires-Dist: pyyaml
Requires-Dist: tqdm
